simplerpyc/__init__.py
simplerpyc/_version.py
simplerpyc/client/__init__.py
simplerpyc/client/connection.py
simplerpyc/client/patcher.py
simplerpyc/client/proxy.py
simplerpyc/common/__init__.py
simplerpyc/common/serialization.py
simplerpyc/server/__init__.py
simplerpyc/server/__main__.py
simplerpyc/server/executor.py
simplerpyc/server/server.py
simplerpyc-0.0.1a3.dist-info/METADATA
simplerpyc-0.0.1a3.dist-info/WHEEL
simplerpyc-0.0.1a3.dist-info/licenses/LICENSE
simplerpyc-0.0.1a3.dist-info/RECORD
