Metadata-Version: 2.4
Name: simplerpyc
Version: 0.0.1a3
Summary: Simple Remote Python Call - WebSocket-based RPC with transparent proxies
Author-email: Suhwan Choi <milkclouds00@gmail.com>
License-File: LICENSE
Classifier: Development Status :: 4 - Beta
Classifier: Intended Audience :: Developers
Classifier: Intended Audience :: Science/Research
Classifier: License :: OSI Approved :: MIT License
Classifier: Operating System :: OS Independent
Classifier: Programming Language :: Python :: 3
Classifier: Programming Language :: Python :: 3.10
Classifier: Programming Language :: Python :: 3.11
Classifier: Programming Language :: Python :: 3.12
Classifier: Programming Language :: Python :: 3.13
Classifier: Topic :: Multimedia :: Graphics
Classifier: Topic :: Multimedia :: Video
Classifier: Topic :: Scientific/Engineering
Classifier: Topic :: Software Development :: Libraries :: Python Modules
Classifier: Typing :: Typed
Requires-Python: >=3.10
Requires-Dist: dill>=0.3.0
Requires-Dist: msgpack-numpy>=0.4.8
Requires-Dist: msgpack>=1.0.0
Requires-Dist: websockets>=12.0
